LICENSE
README.md
setup.py
aep/web/__init__.py
aep/web/arguments.py
aep/web/data.py
aep/web/server.py
aep/web/static/bulma.css
aep/web/templates/error.html
aep/web/templates/form.html
aep/web/templates/generate.html
aep/web/templates/index.html
aep/web/templates/simulation.html
aep/web/templates/upload.html
aep/web/templates/upload_navigator_form.html
aep_web.egg-info/PKG-INFO
aep_web.egg-info/SOURCES.txt
aep_web.egg-info/dependency_links.txt
aep_web.egg-info/entry_points.txt
aep_web.egg-info/namespace_packages.txt
aep_web.egg-info/requires.txt
aep_web.egg-info/top_level.txt
aep_web.egg-info/zip-safe