Metadata-Version: 2.1
Name: aep-web
Version: 0.0.5
Summary: Adversary Emulation Planner (AEP) Web Frontend
Home-page: https://github.com/mnemonic-no/aep-web
Author: mnemonic AS
Author-email: opensource@mnemonic.no
License: MIT
Keywords: aep,attack,mnemonic,web
Platform: UNKNOWN
Classifier: Development Status :: 4 - Beta
Classifier: Topic :: Utilities
Classifier: License :: OSI Approved :: ISC License (ISCL)
Requires-Python: >=3.6, <4
License-File: LICENSE
